Metadata-Version: 2.1
Name: pai-easy-rec
Version: 0.7.1
Summary: An easy-to-use framework for Recommendation
Home-page: https://github.com/alibaba/EasyRec
Author: EasyRec Team
Author-email: easy_rec@alibaba-inc.com
License: UNKNOWN
Platform: UNKNOWN
Classifier: Programming Language :: Python :: 2
Classifier: Programming Language :: Python :: 3
Requires-Dist: eas-prediction
Requires-Dist: future
Requires-Dist: matplotlib
Requires-Dist: oss2
Requires-Dist: pandas
Requires-Dist: psutil
Requires-Dist: pyodps
Requires-Dist: PyYAML
Requires-Dist: scikit-learn
Requires-Dist: xlrd (>=0.9.0)
Provides-Extra: all
Requires-Dist: eas-prediction ; extra == 'all'
Requires-Dist: future ; extra == 'all'
Requires-Dist: matplotlib ; extra == 'all'
Requires-Dist: oss2 ; extra == 'all'
Requires-Dist: pandas ; extra == 'all'
Requires-Dist: psutil ; extra == 'all'
Requires-Dist: pyodps ; extra == 'all'
Requires-Dist: PyYAML ; extra == 'all'
Requires-Dist: scikit-learn ; extra == 'all'
Requires-Dist: xlrd (>=0.9.0) ; extra == 'all'
Provides-Extra: tests
Requires-Dist: configparser ; extra == 'tests'
Requires-Dist: docformatter ; extra == 'tests'
Requires-Dist: flake8 ; extra == 'tests'
Requires-Dist: flake8-docstrings ; extra == 'tests'
Requires-Dist: isort (==4.3.21) ; extra == 'tests'
Requires-Dist: pre-commit ; extra == 'tests'
Requires-Dist: yapf ; extra == 'tests'
Requires-Dist: mdformat ; (python_version > "3") and extra == 'tests'
Requires-Dist: mdformat-tables ; (python_version > "3") and extra == 'tests'
